oco2peak/__init__.py
oco2peak/_nbdev-old.py
oco2peak/_nbdev.py
oco2peak/datasets.py
oco2peak/find_peak.py
oco2peak/find_source.py
oco2peak/nc4_convert.py
oco2peak/oco2map.py
oco2peak/oco2mapfolium.py
oco2peak-0.0.4.dist-info/LICENSE
oco2peak-0.0.4.dist-info/METADATA
oco2peak-0.0.4.dist-info/WHEEL
oco2peak-0.0.4.dist-info/entry_points.txt
oco2peak-0.0.4.dist-info/top_level.txt
oco2peak-0.0.4.dist-info/RECORD
