Metadata-Version: 2.1
Name: oco2peak
Version: 0.0.4
Summary: OCO-2 Satellite CO2 peak detector.
Home-page: https://github.com/dataforgoodfr/batch7_satellite_ges/tree/master/
Author: Alix, Amélie, Benoît, Charlotte, Christian, Quentin, Raphaele, ...
Author-email: nobody@nowhere.com
License: Apache Software License 2.0
Keywords: CO2 satellite
Platform: UNKNOWN
Classifier: Development Status :: 3 - Alpha
Classifier: Intended Audience :: Developers
Classifier: License :: OSI Approved :: Apache Software License
Classifier: Natural Language :: English
Classifier: Programming Language :: Python :: 3.7
Classifier: Programming Language :: Python :: 3.8
Requires-Python: >=3.7
